DFlipFlop.v
// Active reset low D Flip-Flop
module DFlipFlop(q, qBar, D, clk, rst);
	input D, clk, rst;
	output q, qBar;
	reg q;
	not n1 (qBar, q);
		always@ (negedge rst or posedge clk)
		begin
			if(!rst)
				q = 0;
			else
				q = D;
		end
endmodule

SynchronousDownCounter.v
// Keegan Griffee
// Joe Jimenez
// Sean Leisle
// EE 371
// Lab 1: 4 stage synchronous Johnson down counter
// A 4 stage synchronous Johnson down counter with active low reset

module SynchronousDownCounter (out, clk, rst);
	input clk, rst;
	output [3:0] out;
	wire [3:0] qBar;
	wire [3:0] nVal;
	
	assign nVal[0] = qBar[0];
	assign nVal[1] = ~ (out[0] ^ out[1]);
	assign nVal[2] = (out[2] & (out[0] | out[1])) | (qBar[2] & (qBar[0] & qBar[1]));
	assign nVal[3] = (out[3] & (out[0] | out[1] | out[2])) | (qBar[3] & (qBar[0] & qBar[1] & qBar[2]));
	
	DFlipFlop qBar0(out[0], qBar[0], nVal[0], clk, rst);
	DFlipFlop qBar1(out[1], qBar[1], nVal[1], clk, rst);
	DFlipFlop qBar2(out[2], qBar[2], nVal[2], clk, rst);
	DFlipFlop qBar3(out[3], qBar[3], nVal[3], clk, rst);
	
endmodule

SynchronousDownCounterTestBench.v
// Synchronous Down Counter Top Level file for 
// testing and simulation
`include "DFlipFlop.v"
`include "SynchronousDownCounter.v"
module SynchronousDownCounterTestBench;
	wire clk, rst;
	wire [3:0] out;
	// declare an instance of the counter module
	SynchronousDownCounter dut(out[3:0], clk, rst);
	// declare an instance of the Tester module
	Tester aTester (clk, rst, out[3:0]);
	// file for gtkwave
	initial
		begin
		// file for gtkwave signals
		$dumpfile("SynchronousDownCounter.vcd");
		$dumpvars(1,dut);
	end
endmodule 

module Tester(clk, rst, out);
	input [3:0] out;
	output clk, rst;
	reg clk, rst;
	// Clock speed
	parameter stimDelay = 10;
	integer i;
	initial begin
		clk=0;
		// Begin running instructions
		#stimDelay;
		#stimDelay rst = 0; 
		#stimDelay rst = 1;
		// Run long enough to see all states of the counter
		for (i=0; i<36; i=i+1) begin
			#stimDelay;
		end 
		#stimDelay rst = 0;
		#stimDelay;
		#stimDelay;
		$finish;
	end
	// Clock set-up
	always
	begin
		#stimDelay clk=~clk;
	end
endmodule

SynchronousDownCounter.vcd
$date
	Wed Jan 11 15:48:45 2017
$end
$version
	Icarus Verilog
$end
$timescale
	1s
$end
$scope module SynchronousDownCounterTestBench $end
$scope module dut $end
$var wire 1 ! clk $end
$var wire 1 " rst $end
$var wire 4 # qBar [3:0] $end
$var wire 4 $ out [3:0] $end
$var wire 4 % nVal [3:0] $end
$upscope $end
$upscope $end
$enddefinitions $end
#0
$dumpvars
bx %
bx $
bx #
x"
0!
$end
#10
1!
#20
b1111 %
b1111 #
b0 $
0!
0"
#30
b1110 %
b0 #
b1111 $
1!
1"
#40
0!
#50
b1101 %
b1 #
b1110 $
1!
#60
0!
#70
b1100 %
b10 #
b1101 $
1!
#80
0!
#90
b1011 %
b11 #
b1100 $
1!
#100
0!
#110
b1010 %
b100 #
b1011 $
1!
#120
0!
#130
b1001 %
b101 #
b1010 $
1!
#140
0!
#150
b1000 %
b110 #
b1001 $
1!
#160
0!
#170
b111 %
b111 #
b1000 $
1!
#180
0!
#190
b110 %
b1000 #
b111 $
1!
#200
0!
#210
b101 %
b1001 #
b110 $
1!
#220
0!
#230
b100 %
b1010 #
b101 $
1!
#240
0!
#250
b11 %
b1011 #
b100 $
1!
#260
0!
#270
b10 %
b1100 #
b11 $
1!
#280
0!
#290
b1 %
b1101 #
b10 $
1!
#300
0!
#310
b0 %
b1110 #
b1 $
1!
#320
0!
#330
b1111 %
b1111 #
b0 $
1!
#340
0!
#350
b1110 %
b0 #
b1111 $
1!
#360
0!
#370
b1101 %
b1 #
b1110 $
1!
#380
0!
#390
b1100 %
b10 #
b1101 $
1!
#400
b1111 %
b1111 #
b0 $
0!
0"
